enoppy/__init__.py
enoppy/engineer.py
enoppy/paper_based/__init__.py
enoppy/paper_based/ihaoavoa_2022.py
enoppy/paper_based/moeosma_2023.py
enoppy/paper_based/pdo_2022.py
enoppy/paper_based/rwco_2020.py
enoppy/utils/__init__.py
enoppy/utils/encoder.py
enoppy/utils/validator.py
enoppy-0.1.1.dist-info/LICENSE
enoppy-0.1.1.dist-info/METADATA
enoppy-0.1.1.dist-info/WHEEL
enoppy-0.1.1.dist-info/top_level.txt
enoppy-0.1.1.dist-info/RECORD
