Metadata-Version: 2.1
Name: enoppy
Version: 0.1.1
Summary: ENOPPY: A Python Library for Engineering Optimization Problems
Home-page: https://github.com/thieu1995/enoppy
Author: Thieu
Author-email: nguyenthieu2102@gmail.com
License: GPLv3
Project-URL: Documentation, https://enoppy.readthedocs.io/
Project-URL: Source Code, https://github.com/thieu1995/enoppy
Project-URL: Bug Tracker, https://github.com/thieu1995/enoppy/issues
Project-URL: Change Log, https://github.com/thieu1995/enoppy/blob/master/ChangeLog.md
Project-URL: Forum, https://t.me/+fRVCJGuGJg1mNDg1
Keywords: engineering optimization problems,mathematical optimization,Tension/compression spring design problem,Welded beam design problem,Industrial chemical process problems,Process design and synthesis problems,Mechanical design problems,Power system problems,Power electronics: synchronous optimal pulse-width modulation,Livestock feed ration optimization,Rolling element bearing design problem,multi-objectives optimization problems,Constrained optimization,Stochastic optimization,Global optimi
Classifier: Development Status :: 5 - Production/Stable
Classifier: Intended Audience :: Developers
Classifier: Intended Audience :: Education
Classifier: Intended Audience :: Information Technology
Classifier: Intended Audience :: Science/Research
Classifier: License :: OSI Approved :: GNU General Public License v3 (GPLv3)
Classifier: Natural Language :: English
Classifier: Programming Language :: Python :: 3
Classifier: Programming Language :: Python :: 3.7
Classifier: Programming Language :: Python :: 3.8
Classifier: Programming Language :: Python :: 3.9
Classifier: Programming Language :: Python :: 3.10
Classifier: Programming Language :: Python :: 3.11
Classifier: Topic :: System :: Benchmark
Classifier: Topic :: Scientific/Engineering
Classifier: Topic :: Scientific/Engineering :: Mathematics
Classifier: Topic :: Scientific/Engineering :: Artificial Intelligence
Classifier: Topic :: Scientific/Engineering :: Information Analysis
Classifier: Topic :: Scientific/Engineering :: Visualization
Classifier: Topic :: Scientific/Engineering :: Bio-Informatics
Classifier: Topic :: Software Development :: Build Tools
Classifier: Topic :: Software Development :: Libraries
Classifier: Topic :: Software Development :: Libraries :: Python Modules
Classifier: Topic :: Utilities
Requires-Python: >=3.7
License-File: LICENSE
Requires-Dist: numpy (>=1.17.1)
Requires-Dist: matplotlib (>=3.3.0)
Requires-Dist: scipy (>=1.7.1)
Requires-Dist: mealpy (>=2.5.3)
Requires-Dist: opfunu (>=1.0.0)
Provides-Extra: dev
Requires-Dist: pytest (>=7.0) ; extra == 'dev'
Requires-Dist: twine (>=4.0.1) ; extra == 'dev'
